{
	"$schema": "http://schema.management.azure.com/schemas/2015-01-01/deploymentTemplate.json#",
	"contentVersion": "1.0.0.0",
	"parameters": {
		"factoryName": {
			"type": "string",
			"metadata": "Data Factory name",
			"defaultValue": "ADFWH-UPS"
		}
	},
	"variables": {
		"factoryId": "[concat('Microsoft.DataFactory/factories/', parameters('factoryName'))]"
	},
	"resources": [
		{
			"name": "[concat(parameters('factoryName'), '/crea_df_programa_delta')]",
			"type": "Microsoft.DataFactory/factories/pipelines",
			"apiVersion": "2018-06-01",
			"properties": {
				"activities": [
					{
						"name": "VIEW_DIM_TO_PARQUET",
						"type": "Copy",
						"dependsOn": [],
						"policy": {
							"timeout": "0.12:00:00",
							"retry": 0,
							"retryIntervalInSeconds": 30,
							"secureOutput": false,
							"secureInput": false
						},
						"userProperties": [
							{
								"name": "Source",
								"value": "REPLICA_SCHEMA.VIEW_DIM_PROGRAMA_ACADEMICO"
							},
							{
								"name": "Destination",
								"value": "container-ins-mat/vdirectory_dim_programa_academico/DIM_PROGRAMA_ACADEMICO.parquet"
							}
						],
						"typeProperties": {
							"source": {
								"type": "PostgreSqlV2Source",
								"queryTimeout": "02:00:00"
							},
							"sink": {
								"type": "ParquetSink",
								"storeSettings": {
									"type": "AzureBlobStorageWriteSettings"
								},
								"formatSettings": {
									"type": "ParquetWriteSettings"
								}
							},
							"enableStaging": false,
							"translator": {
								"type": "TabularTranslator",
								"mappings": [
									{
										"source": {
											"name": "codigo_interno_programa_academico",
											"type": "String",
											"physicalType": "character varying"
										},
										"sink": {
											"name": "codigo_interno_programa_academico",
											"type": "String",
											"physicalType": "UTF8"
										}
									},
									{
										"source": {
											"name": "carrera",
											"type": "String",
											"physicalType": "character varying"
										},
										"sink": {
											"name": "carrera",
											"type": "String",
											"physicalType": "UTF8"
										}
									},
									{
										"source": {
											"name": "sede",
											"type": "String",
											"physicalType": "character varying"
										},
										"sink": {
											"name": "sede",
											"type": "String",
											"physicalType": "UTF8"
										}
									},
									{
										"source": {
											"name": "campus",
											"type": "String",
											"physicalType": "character varying"
										},
										"sink": {
											"name": "campus",
											"type": "String",
											"physicalType": "UTF8"
										}
									},
									{
										"source": {
											"name": "duracion_en_semestres",
											"type": "Int32",
											"physicalType": "integer"
										},
										"sink": {
											"name": "duracion_en_semestres",
											"type": "Int32",
											"physicalType": "INT_32"
										}
									},
									{
										"source": {
											"name": "duracion_en_anios",
											"type": "Decimal",
											"physicalType": "numeric"
										},
										"sink": {
											"name": "duracion_en_anios",
											"type": "Decimal",
											"physicalType": "DECIMAL"
										}
									},
									{
										"source": {
											"name": "modalidad",
											"type": "String",
											"physicalType": "character varying"
										},
										"sink": {
											"name": "modalidad",
											"type": "String",
											"physicalType": "UTF8"
										}
									},
									{
										"source": {
											"name": "tipo_proyecto_educacion",
											"type": "String",
											"physicalType": "character varying"
										},
										"sink": {
											"name": "tipo_proyecto_educacion",
											"type": "String",
											"physicalType": "UTF8"
										}
									},
									{
										"source": {
											"name": "proyecto_educacion",
											"type": "String",
											"physicalType": "character varying"
										},
										"sink": {
											"name": "proyecto_educacion",
											"type": "String",
											"physicalType": "UTF8"
										}
									},
									{
										"source": {
											"name": "vigencia_proyecto_educacion",
											"type": "String",
											"physicalType": "character varying"
										},
										"sink": {
											"name": "vigencia_proyecto_educacion",
											"type": "String",
											"physicalType": "UTF8"
										}
									},
									{
										"source": {
											"name": "aud_fecha_adicion",
											"type": "DateTime",
											"physicalType": "date"
										},
										"sink": {
											"name": "aud_fecha_adicion",
											"type": "DateTime",
											"physicalType": "INT_96"
										}
									},
									{
										"source": {
											"name": "aud_fecha_modificacion",
											"type": "DateTime",
											"physicalType": "date"
										},
										"sink": {
											"name": "aud_fecha_modificacion",
											"type": "DateTime",
											"physicalType": "INT_96"
										}
									}
								],
								"typeConversion": true,
								"typeConversionSettings": {
									"allowDataTruncation": true,
									"treatBooleanAsNumber": false
								}
							}
						},
						"inputs": [
							{
								"referenceName": "VIEW_PROGRAMA_ACADEMICO",
								"type": "DatasetReference",
								"parameters": {}
							}
						],
						"outputs": [
							{
								"referenceName": "DIM_PROGRAMA_ACADEMICO",
								"type": "DatasetReference",
								"parameters": {}
							}
						]
					},
					{
						"name": "Data flow1",
						"type": "ExecuteDataFlow",
						"dependsOn": [
							{
								"activity": "VIEW_DIM_TO_PARQUET",
								"dependencyConditions": [
									"Succeeded"
								]
							}
						],
						"policy": {
							"timeout": "0.12:00:00",
							"retry": 0,
							"retryIntervalInSeconds": 30,
							"secureOutput": false,
							"secureInput": false
						},
						"userProperties": [],
						"typeProperties": {
							"dataflow": {
								"referenceName": "df_programa_academico_delta",
								"type": "DataFlowReference",
								"parameters": {},
								"datasetParameters": {
									"source1": {},
									"ParquePrrogramaFinal": {}
								}
							},
							"staging": {},
							"compute": {
								"coreCount": 8,
								"computeType": "General"
							},
							"traceLevel": "Fine"
						}
					},
					{
						"name": "Parquet_LookUPS",
						"type": "Copy",
						"dependsOn": [
							{
								"activity": "Data flow1",
								"dependencyConditions": [
									"Succeeded"
								]
							}
						],
						"policy": {
							"timeout": "0.12:00:00",
							"retry": 0,
							"retryIntervalInSeconds": 30,
							"secureOutput": false,
							"secureInput": false
						},
						"userProperties": [],
						"typeProperties": {
							"source": {
								"type": "ParquetSource",
								"storeSettings": {
									"type": "AzureBlobStorageReadSettings",
									"recursive": true,
									"enablePartitionDiscovery": false
								},
								"formatSettings": {
									"type": "ParquetReadSettings"
								}
							},
							"sink": {
								"type": "AzurePostgreSqlSink",
								"writeBatchSize": 1000000,
								"writeBatchTimeout": "00:30:00",
								"writeMethod": "CopyCommand"
							},
							"enableStaging": false,
							"translator": {
								"type": "TabularTranslator",
								"mappings": [
									{
										"source": {
											"name": "codigo_interno_programa_academico",
											"type": "String",
											"physicalType": "UTF8"
										},
										"sink": {
											"name": "codigo_interno_programa_academico",
											"type": "String",
											"physicalType": "character varying"
										}
									},
									{
										"source": {
											"name": "carrera",
											"type": "String",
											"physicalType": "UTF8"
										},
										"sink": {
											"name": "nombre_programa_academico",
											"type": "String",
											"physicalType": "character varying"
										}
									},
									{
										"source": {
											"name": "sede",
											"type": "String",
											"physicalType": "UTF8"
										},
										"sink": {
											"name": "sede_programa_academico",
											"type": "String",
											"physicalType": "character varying"
										}
									},
									{
										"source": {
											"name": "campus",
											"type": "String",
											"physicalType": "UTF8"
										},
										"sink": {
											"name": "campus_extension_programa_academico",
											"type": "String",
											"physicalType": "character varying"
										}
									},
									{
										"source": {
											"name": "duracion_en_semestres",
											"type": "Int32",
											"physicalType": "INT32"
										},
										"sink": {
											"name": "duracion_programa_semestres",
											"type": "Decimal",
											"physicalType": "numeric"
										}
									},
									{
										"source": {
											"name": "duracion_en_anios",
											"type": "Decimal",
											"physicalType": "DECIMAL",
											"scale": 2,
											"precision": 18
										},
										"sink": {
											"name": "duracion_programa_anio",
											"type": "Decimal",
											"physicalType": "numeric"
										}
									},
									{
										"source": {
											"name": "modalidad",
											"type": "String",
											"physicalType": "UTF8"
										},
										"sink": {
											"name": "modalidad_programa_academico",
											"type": "String",
											"physicalType": "character varying"
										}
									},
									{
										"source": {
											"name": "tipo_proyecto_educacion",
											"type": "String",
											"physicalType": "UTF8"
										},
										"sink": {
											"name": "tipo_proyecto_educacion",
											"type": "String",
											"physicalType": "character varying"
										}
									},
									{
										"source": {
											"name": "proyecto_educacion",
											"type": "String",
											"physicalType": "UTF8"
										},
										"sink": {
											"name": "proyecto_educacion",
											"type": "String",
											"physicalType": "character varying"
										}
									},
									{
										"source": {
											"name": "vigencia_proyecto_educacion",
											"type": "Boolean",
											"physicalType": "BOOLEAN"
										},
										"sink": {
											"name": "vigencia_proyecto_educacion",
											"type": "Boolean",
											"physicalType": "boolean"
										}
									},
									{
										"source": {
											"name": "aud_fecha_adicion",
											"type": "DateTime",
											"physicalType": "DATE"
										},
										"sink": {
											"name": "fecha_adicion",
											"type": "DateTime",
											"physicalType": "date"
										}
									},
									{
										"source": {
											"name": "aud_fecha_modificacion",
											"type": "DateTime",
											"physicalType": "DATE"
										},
										"sink": {
											"name": "fecha_modificacion",
											"type": "DateTime",
											"physicalType": "date"
										}
									},
									{
										"source": {
											"name": "HASH",
											"type": "String",
											"physicalType": "UTF8"
										},
										"sink": {
											"name": "hash",
											"type": "String",
											"physicalType": "text"
										}
									},
									{
										"source": {
											"name": "FECHA_ULTIMA_ACTUALIZACION",
											"type": "DateTime",
											"physicalType": "INT96"
										},
										"sink": {
											"name": "fecha_ultima_modificacion",
											"type": "DateTime",
											"physicalType": "date"
										}
									},
									{
										"source": {
											"name": "LINAJE",
											"type": "String",
											"physicalType": "UTF8"
										},
										"sink": {
											"name": "linaje",
											"type": "String",
											"physicalType": "text"
										}
									}
								],
								"typeConversion": true,
								"typeConversionSettings": {
									"allowDataTruncation": true,
									"treatBooleanAsNumber": false
								}
							}
						},
						"inputs": [
							{
								"referenceName": "DIM_PROGRAMA_ACADEMICO_FINAL",
								"type": "DatasetReference",
								"parameters": {}
							}
						],
						"outputs": [
							{
								"referenceName": "AZ_PG_PROGRAMA_ACADEMICO_LOOUKPS",
								"type": "DatasetReference",
								"parameters": {}
							}
						]
					}
				],
				"policy": {
					"elapsedTimeMetric": {}
				},
				"folder": {
					"name": "DIM_PROGRAMA_ACADEMICO"
				},
				"annotations": [],
				"lastPublishTime": "2025-07-02T15:48:13Z"
			},
			"dependsOn": []
		},
		{
			"name": "[concat(parameters('factoryName'), '/OrquestadorDiario')]",
			"type": "Microsoft.DataFactory/factories/pipelines",
			"apiVersion": "2018-06-01",
			"properties": {
				"activities": [
					{
						"name": "Execute Pipeline Delta Postulante",
						"type": "ExecutePipeline",
						"dependsOn": [],
						"policy": {
							"secureInput": false
						},
						"userProperties": [],
						"typeProperties": {
							"pipeline": {
								"referenceName": "crea_df_postulante_delta",
								"type": "PipelineReference"
							},
							"waitOnCompletion": true,
							"parameters": {}
						}
					},
					{
						"name": "Execute Pipeline Delta Programa",
						"type": "ExecutePipeline",
						"dependsOn": [],
						"policy": {
							"secureInput": false
						},
						"userProperties": [],
						"typeProperties": {
							"pipeline": {
								"referenceName": "crea_df_programa_delta",
								"type": "PipelineReference"
							},
							"waitOnCompletion": true,
							"parameters": {}
						}
					},
					{
						"name": "Execute Pipeline Delta Periodp",
						"type": "ExecutePipeline",
						"dependsOn": [],
						"policy": {
							"secureInput": false
						},
						"userProperties": [],
						"typeProperties": {
							"pipeline": {
								"referenceName": "crea_df_periodo_delta",
								"type": "PipelineReference"
							},
							"waitOnCompletion": true,
							"parameters": {}
						}
					}
				],
				"policy": {
					"elapsedTimeMetric": {}
				},
				"folder": {
					"name": "Orquestadores"
				},
				"annotations": []
			},
			"dependsOn": [
				"[concat(variables('factoryId'), '/pipelines/crea_df_programa_delta')]"
			]
		},
		{
			"name": "[concat(parameters('factoryName'), '/actualizalookuppostulante')]",
			"type": "Microsoft.DataFactory/factories/triggers",
			"apiVersion": "2018-06-01",
			"properties": {
				"description": "actualizar la tabla en relación de una fecha y tiempo determinada",
				"annotations": [],
				"runtimeState": "Started",
				"pipelines": [
					{
						"pipelineReference": {
							"referenceName": "crea_carga_full_postulante",
							"type": "PipelineReference"
						},
						"parameters": {}
					}
				],
				"type": "ScheduleTrigger",
				"typeProperties": {
					"recurrence": {
						"frequency": "Day",
						"interval": 1,
						"startTime": "2025-06-02T22:35:00",
						"timeZone": "SA Pacific Standard Time",
						"schedule": {
							"minutes": [
								37
							],
							"hours": [
								11
							]
						}
					}
				}
			},
			"dependsOn": []
		}
	]
}